LICENSE
MANIFEST.in
setup.py
sq_protos_py.egg-info/PKG-INFO
sq_protos_py.egg-info/SOURCES.txt
sq_protos_py.egg-info/dependency_links.txt
sq_protos_py.egg-info/top_level.txt
sq_protos_py/google/protobuf/__init__.py
sq_protos_py/google/protobuf/descriptor.py
sq_protos_py/google/protobuf/descriptor_database.py
sq_protos_py/google/protobuf/descriptor_pool.py
sq_protos_py/google/protobuf/json_format.py
sq_protos_py/google/protobuf/message.py
sq_protos_py/google/protobuf/message_factory.py
sq_protos_py/google/protobuf/proto_builder.py
sq_protos_py/google/protobuf/reflection.py
sq_protos_py/google/protobuf/service.py
sq_protos_py/google/protobuf/service_reflection.py
sq_protos_py/google/protobuf/symbol_database.py
sq_protos_py/google/protobuf/text_encoding.py
sq_protos_py/google/protobuf/text_format.py
sq_protos_py/google/protobuf/unknown_fields.py
sq_protos_py/google/protobuf/__pycache__/__init__.cpython-310.pyc
sq_protos_py/google/protobuf/__pycache__/__init__.cpython-312.pyc
sq_protos_py/google/protobuf/compiler/__init__.py
sq_protos_py/google/protobuf/internal/__init__.py
sq_protos_py/google/protobuf/internal/_parameterized.py
sq_protos_py/google/protobuf/internal/any_test.proto
sq_protos_py/google/protobuf/internal/api_implementation.cc
sq_protos_py/google/protobuf/internal/api_implementation.py
sq_protos_py/google/protobuf/internal/builder.py
sq_protos_py/google/protobuf/internal/containers.py
sq_protos_py/google/protobuf/internal/decoder.py
sq_protos_py/google/protobuf/internal/descriptor_database_test.py
sq_protos_py/google/protobuf/internal/descriptor_pool_test.py
sq_protos_py/google/protobuf/internal/descriptor_pool_test1.proto
sq_protos_py/google/protobuf/internal/descriptor_pool_test2.proto
sq_protos_py/google/protobuf/internal/descriptor_test.py
sq_protos_py/google/protobuf/internal/encoder.py
sq_protos_py/google/protobuf/internal/enum_type_wrapper.py
sq_protos_py/google/protobuf/internal/extension_dict.py
sq_protos_py/google/protobuf/internal/factory_test1.proto
sq_protos_py/google/protobuf/internal/factory_test2.proto
sq_protos_py/google/protobuf/internal/field_mask.py
